{
  "notifications": [
    {
      "id": 1,
      "title": "系统维护通知",
      "content": "系统将于本周六凌晨2点至4点进行维护，届时服务将不可用。请提前做好安排。",
      "date": "2023-10-21T02:00:00"
    },
    {
      "id": 2,
      "title": "新功能上线",
      "content": "我们刚刚发布了新的用户界面，增加了多项实用功能。欢迎体验并提供反馈。",
      "date": "2023-10-20T15:30:00"
    },
    {
      "id": 3,
      "title": "欢迎使用通知系统",
      "content": "这是您的第一条通知，系统运行正常。如有任何问题，请联系管理员。",
      "date": "2023-10-19T09:00:00"
    },
    {
      "id": 4,
      "title": "会议提醒",
      "content": "本周五下午3点将在会议室A举行项目进度汇报会议，请相关人员准时参加。",
      "date": "2023-10-18T14:20:00"
    }
  ]
}
